JyPlotter-0.9.4.dist-info/DESCRIPTION.rst
JyPlotter-0.9.4.dist-info/METADATA
JyPlotter-0.9.4.dist-info/RECORD
JyPlotter-0.9.4.dist-info/WHEEL
JyPlotter-0.9.4.dist-info/metadata.json
JyPlotter-0.9.4.dist-info/top_level.txt
PyPlotter/Colors.py
PyPlotter/Compatibility.py
PyPlotter/Gfx.py
PyPlotter/Graph.py
PyPlotter/Simplex.py
PyPlotter/__init__.py
PyPlotter/altsets.py
PyPlotter/awtGfx.py
PyPlotter/gtkGfx.py
PyPlotter/gtkSupport.py
PyPlotter/psGfx.py
PyPlotter/qtGfx.py
PyPlotter/sets.py
PyPlotter/systemTest.py
PyPlotter/tkGfx.py
PyPlotter/wxGfx.py
